deckbuilder/CardGenerator.py
deckbuilder/DeckBuilder.py
deckbuilder/Gloss.py
deckbuilder/__init__.py
deckbuilder/__main__.py
deckbuilder/glosser_test.py
Japanese_Deck_Builder-1.0.0.dist-info/LICENSE.txt
Japanese_Deck_Builder-1.0.0.dist-info/METADATA
Japanese_Deck_Builder-1.0.0.dist-info/WHEEL
Japanese_Deck_Builder-1.0.0.dist-info/entry_points.txt
Japanese_Deck_Builder-1.0.0.dist-info/top_level.txt
Japanese_Deck_Builder-1.0.0.dist-info/RECORD
